setup.cfg
setup.py
Beetle_Sitemap.egg-info/PKG-INFO
Beetle_Sitemap.egg-info/SOURCES.txt
Beetle_Sitemap.egg-info/dependency_links.txt
Beetle_Sitemap.egg-info/top_level.txt
beetle_sitemap/__init__.py