Metadata-Version: 1.1
Name: Beetle-Sitemap
Version: 1.0.0
Summary: Enables Beetle to generate a sitemap.xml file
Home-page: https://github.com/Tenzer/beetle-sitemap
Author: Jeppe Toustrup
Author-email: jeppe@tenzer.dk
License: MIT
Platform: UNKNOWN
Classifier: Development Status :: 4 - Beta
Classifier: Intended Audience :: Developers
Classifier: Topic :: Internet :: WWW/HTTP
Classifier: Topic :: Text Processing :: Indexing
Classifier: Topic :: Text Processing :: Markup :: XML
Classifier: License :: OSI Approved :: MIT License
Classifier: Programming Language :: Python :: 2
Classifier: Programming Language :: Python :: 2.6
Classifier: Programming Language :: Python :: 2.7
Classifier: Programming Language :: Python :: 3
Classifier: Programming Language :: Python :: 3.3
Classifier: Programming Language :: Python :: 3.4
